odoo10_addon_account_cutoff_accrual_base-10.0.1.1.0-py2.7-nspkg.pth
odoo/addons/account_cutoff_accrual_base/README.rst
odoo/addons/account_cutoff_accrual_base/__init__.py
odoo/addons/account_cutoff_accrual_base/__manifest__.py
odoo/addons/account_cutoff_accrual_base/i18n/account_cutoff_accrual_base.pot
odoo/addons/account_cutoff_accrual_base/i18n/am.po
odoo/addons/account_cutoff_accrual_base/i18n/ar.po
odoo/addons/account_cutoff_accrual_base/i18n/ca.po
odoo/addons/account_cutoff_accrual_base/i18n/de.po
odoo/addons/account_cutoff_accrual_base/i18n/el_GR.po
odoo/addons/account_cutoff_accrual_base/i18n/es.po
odoo/addons/account_cutoff_accrual_base/i18n/es_ES.po
odoo/addons/account_cutoff_accrual_base/i18n/es_MX.po
odoo/addons/account_cutoff_accrual_base/i18n/fi.po
odoo/addons/account_cutoff_accrual_base/i18n/fr.po
odoo/addons/account_cutoff_accrual_base/i18n/fr_FR.po
odoo/addons/account_cutoff_accrual_base/i18n/hr.po
odoo/addons/account_cutoff_accrual_base/i18n/hr_HR.po
odoo/addons/account_cutoff_accrual_base/i18n/it.po
odoo/addons/account_cutoff_accrual_base/i18n/nb.po
odoo/addons/account_cutoff_accrual_base/i18n/nb_NO.po
odoo/addons/account_cutoff_accrual_base/i18n/nl.po
odoo/addons/account_cutoff_accrual_base/i18n/nl_BE.po
odoo/addons/account_cutoff_accrual_base/i18n/nl_NL.po
odoo/addons/account_cutoff_accrual_base/i18n/pt.po
odoo/addons/account_cutoff_accrual_base/i18n/pt_BR.po
odoo/addons/account_cutoff_accrual_base/i18n/pt_PT.po
odoo/addons/account_cutoff_accrual_base/i18n/ro.po
odoo/addons/account_cutoff_accrual_base/i18n/sk.po
odoo/addons/account_cutoff_accrual_base/i18n/sl.po
odoo/addons/account_cutoff_accrual_base/i18n/tr.po
odoo/addons/account_cutoff_accrual_base/i18n/tr_TR.po
odoo/addons/account_cutoff_accrual_base/i18n/zh_CN.po
odoo/addons/account_cutoff_accrual_base/models/__init__.py
odoo/addons/account_cutoff_accrual_base/models/account.py
odoo/addons/account_cutoff_accrual_base/models/account_config_settings.py
odoo10_addon_account_cutoff_accrual_base-10.0.1.1.0.dist-info/DESCRIPTION.rst
odoo10_addon_account_cutoff_accrual_base-10.0.1.1.0.dist-info/METADATA
odoo10_addon_account_cutoff_accrual_base-10.0.1.1.0.dist-info/RECORD
odoo10_addon_account_cutoff_accrual_base-10.0.1.1.0.dist-info/WHEEL
odoo10_addon_account_cutoff_accrual_base-10.0.1.1.0.dist-info/metadata.json
odoo10_addon_account_cutoff_accrual_base-10.0.1.1.0.dist-info/namespace_packages.txt
odoo10_addon_account_cutoff_accrual_base-10.0.1.1.0.dist-info/top_level.txt
